torch_testing/__init__.py
torch_testing/assertions.py
torch_testing-0.0.2.dist-info/DESCRIPTION.rst
torch_testing-0.0.2.dist-info/METADATA
torch_testing-0.0.2.dist-info/RECORD
torch_testing-0.0.2.dist-info/WHEEL
torch_testing-0.0.2.dist-info/metadata.json
torch_testing-0.0.2.dist-info/top_level.txt
