Metadata-Version: 2.0
Name: torch-testing
Version: 0.0.2
Summary: A collection of assertion methods to compare PyTorch Tensors in tests
Home-page: https://github.com/the-bass/torch_testing
Author: The Bass
Author-email: the-bass@posteo.co
License: MIT
Platform: UNKNOWN
Classifier: Programming Language :: Python :: 3
Classifier: License :: OSI Approved :: MIT License
Classifier: Operating System :: OS Independent
